backend/problems/sign_magnitude_comparator/solution.v
module sign_magnitude_comparator(input signed [7:0] a, input signed [7:0] b, output gt, output eq, output lt);
  assign gt = a > b;
  assign eq = a == b;
  assign lt = a < b;
endmodule

backend/problems/sign_magnitude_comparator/tb.v
`timescale 1ns/1ps
module tb;
  reg signed [7:0] a;
  reg signed [7:0] b;
  wire gt;
  wire eq;
  wire lt;

  sign_magnitude_comparator dut(.a(a), .b(b), .gt(gt), .eq(eq), .lt(lt));

  initial begin
    $dumpfile("simulation.vcd");
    $dumpvars(0, tb);
    a = 8'd0; b = 8'd0; #1; $display("%b %b %b", gt, eq, lt);
    a = 8'd1; b = 8'd1; #1; $display("%b %b %b", gt, eq, lt);
    a = 8'd255; b = 8'd255; #1; $display("%b %b %b", gt, eq, lt);
    a = 8'd170; b = 8'd170; #1; $display("%b %b %b", gt, eq, lt);
    a = 8'd2; b = 8'd2; #1; $display("%b %b %b", gt, eq, lt);
    a = 8'd3; b = 8'd3; #1; $display("%b %b %b", gt, eq, lt);
    a = 8'd127; b = 8'd127; #1; $display("%b %b %b", gt, eq, lt);
    a = 8'd170; b = 8'd170; #1; $display("%b %b %b", gt, eq, lt);
    $finish;
  end
endmodule

backend/problems/sign_magnitude_comparator/simulation.vcd
$date
	Sat May 16 11:20:02 2026
$end
$version
	Icarus Verilog
$end
$timescale
	1ps
$end
$scope module tb $end
$var wire 1 ! eq $end
$var wire 1 " gt $end
$var wire 1 # lt $end
$var reg 8 $ a [7:0] $end
$var reg 8 % b [7:0] $end
$scope module dut $end
$var wire 8 & a [7:0] $end
$var wire 8 ' b [7:0] $end
$var wire 1 ! eq $end
$var wire 1 " gt $end
$var wire 1 # lt $end
$upscope $end
$upscope $end
$enddefinitions $end
#0
$dumpvars
b0 '
b0 &
b0 %
b0 $
z#
z"
z!
$end
#1000
b1 %
b1 '
b1 $
b1 &
#2000
b11111111 %
b11111111 '
b11111111 $
b11111111 &
#3000
b10101010 %
b10101010 '
b10101010 $
b10101010 &
#4000
b10 %
b10 '
b10 $
b10 &
#5000
b11 %
b11 '
b11 $
b11 &
#6000
b1111111 %
b1111111 '
b1111111 $
b1111111 &
#7000
b10101010 %
b10101010 '
b10101010 $
b10101010 &
