backend/problems/address_incrementer/solution.v
module address_incrementer(input [15:0] addr, input incr, output [15:0] next_addr);
  assign next_addr = incr ? addr + 16'd1 : addr;
endmodule

backend/problems/address_incrementer/tb.v
`timescale 1ns/1ps
module tb;
  reg [15:0] addr;
  reg incr;
  wire [15:0] next_addr;

  address_incrementer dut(.addr(addr), .incr(incr), .next_addr(next_addr));

  initial begin
    $dumpfile("simulation.vcd");
    $dumpvars(0, tb);
    addr = 16'd0; incr = 1'd0; #1; $display("%b", next_addr);
    addr = 16'd1; incr = 1'd1; #1; $display("%b", next_addr);
    addr = 16'd65535; incr = 1'd1; #1; $display("%b", next_addr);
    addr = 16'd170; incr = 1'd0; #1; $display("%b", next_addr);
    addr = 16'd2; incr = 1'd2; #1; $display("%b", next_addr);
    addr = 16'd3; incr = 1'd3; #1; $display("%b", next_addr);
    addr = 16'd32767; incr = 1'd0; #1; $display("%b", next_addr);
    addr = 16'd65450; incr = 1'd0; #1; $display("%b", next_addr);
    $finish;
  end
endmodule

backend/problems/address_incrementer/simulation.vcd
$date
	Sat May 16 11:19:22 2026
$end
$version
	Icarus Verilog
$end
$timescale
	1ps
$end
$scope module tb $end
$var wire 16 ! next_addr [15:0] $end
$var reg 16 " addr [15:0] $end
$var reg 1 # incr $end
$scope module dut $end
$var wire 16 $ addr [15:0] $end
$var wire 1 % incr $end
$var wire 16 & next_addr [15:0] $end
$upscope $end
$upscope $end
$enddefinitions $end
#0
$dumpvars
bz &
0%
b0 $
0#
b0 "
bz !
$end
#1000
1#
1%
b1 "
b1 $
#2000
b1111111111111111 "
b1111111111111111 $
#3000
0#
0%
b10101010 "
b10101010 $
#4000
b10 "
b10 $
#5000
1#
1%
b11 "
b11 $
#6000
0#
0%
b111111111111111 "
b111111111111111 $
#7000
b1111111110101010 "
b1111111110101010 $
