backend/problems/formal_property_checker/solution.v
module formal_property_checker(input [7:0] value, input permit, output reg violation);
  always @(*) begin
    violation = !permit && value > 8'd200;
  end
endmodule

backend/problems/formal_property_checker/tb.v
`timescale 1ns/1ps
module tb;
  reg [7:0] value;
  reg permit;
  wire violation;

  formal_property_checker dut(.value(value), .permit(permit), .violation(violation));

  initial begin
    $dumpfile("simulation.vcd");
    $dumpvars(0, tb);
    value = 8'd0; permit = 0; #1; $display("%b", violation);
    value = 8'd1; permit = 1; #1; $display("%b", violation);
    value = 8'd255; permit = 0; #1; $display("%b", violation);
    value = 8'd170; permit = 1; #1; $display("%b", violation);
    value = 8'd2; permit = 0; #1; $display("%b", violation);
    value = 8'd3; permit = 1; #1; $display("%b", violation);
    value = 8'd127; permit = 0; #1; $display("%b", violation);
    value = 8'd170; permit = 1; #1; $display("%b", violation);
    $finish;
  end
endmodule

backend/problems/formal_property_checker/simulation.vcd
$date
	Sat May 16 11:19:41 2026
$end
$version
	Icarus Verilog
$end
$timescale
	1ps
$end
$scope module tb $end
$var wire 1 ! violation $end
$var reg 1 " permit $end
$var reg 8 # value [7:0] $end
$scope module dut $end
$var wire 1 $ permit $end
$var wire 8 % value [7:0] $end
$var reg 1 & violation $end
$upscope $end
$upscope $end
$enddefinitions $end
#0
$dumpvars
x&
b0 %
0$
b0 #
0"
x!
$end
#1000
1"
1$
b1 #
b1 %
#2000
0"
0$
b11111111 #
b11111111 %
#3000
1"
1$
b10101010 #
b10101010 %
#4000
0"
0$
b10 #
b10 %
#5000
1"
1$
b11 #
b11 %
#6000
0"
0$
b1111111 #
b1111111 %
#7000
1"
1$
b10101010 #
b10101010 %
