backend/problems/find_bug_priority_encoder/solution.v
module find_bug_priority_encoder(input [7:0] in, output reg [2:0] code, output reg valid);
  always @(*) begin
    valid = |in;
    if (in[7]) code = 3'd7;
    else if (in[6]) code = 3'd6;
    else if (in[5]) code = 3'd5;
    else if (in[4]) code = 3'd4;
    else if (in[3]) code = 3'd3;
    else if (in[2]) code = 3'd2;
    else if (in[1]) code = 3'd1;
    else code = 3'd0;
  end
endmodule

backend/problems/find_bug_priority_encoder/tb.v
`timescale 1ns/1ps
module tb;
  reg [7:0] in;
  wire [2:0] code;
  wire valid;

  find_bug_priority_encoder dut(.in(in), .code(code), .valid(valid));

  initial begin
    $dumpfile("simulation.vcd");
    $dumpvars(0, tb);
    in = 8'd0; #1; $display("%b %b", code, valid);
    in = 8'd1; #1; $display("%b %b", code, valid);
    in = 8'd255; #1; $display("%b %b", code, valid);
    in = 8'd170; #1; $display("%b %b", code, valid);
    in = 8'd2; #1; $display("%b %b", code, valid);
    in = 8'd3; #1; $display("%b %b", code, valid);
    in = 8'd127; #1; $display("%b %b", code, valid);
    in = 8'd170; #1; $display("%b %b", code, valid);
    $finish;
  end
endmodule

backend/problems/find_bug_priority_encoder/simulation.vcd
$date
	Sat May 16 11:19:39 2026
$end
$version
	Icarus Verilog
$end
$timescale
	1ps
$end
$scope module tb $end
$var wire 3 ! code [2:0] $end
$var wire 1 " valid $end
$var reg 8 # in [7:0] $end
$scope module dut $end
$var wire 8 $ in [7:0] $end
$var reg 3 % code [2:0] $end
$var reg 1 & valid $end
$upscope $end
$upscope $end
$enddefinitions $end
#0
$dumpvars
x&
bx %
b0 $
b0 #
x"
bx !
$end
#1000
b1 #
b1 $
#2000
b11111111 #
b11111111 $
#3000
b10101010 #
b10101010 $
#4000
b10 #
b10 $
#5000
b11 #
b11 $
#6000
b1111111 #
b1111111 $
#7000
b10101010 #
b10101010 $
